{
  "updated_at": "2026-07-16T06:40:39.925466+00:00",
  "source": "yfinance",
  "variacoes": {},
  "precos": {
    "GOLD": 4035.199951,
    "COPPER": 6.391,
    "CL": 79.559998,
    "OSLO": 2303.26001,
    "ZS": 1199.25,
    "YMH26": 52935.0,
    "GDOW": 52658.640625,
    "VALE.K": 14.67,
    "PBR": 17.860001,
    "EWZ": 35.880001,
    "XLF": 56.560001,
    "XLP": 83.470001,
    "XLE": 56.5,
    "XME": 103.199997,
    "EEM": 65.57,
    "SOXX.O": 555.27002,
    ".BSESN": 77458.398438,
    "CHINA": 3887.23999,
    "MINERIO_SINA": 161.91,
    "DX": 100.497002,
    "VX": 15.67,
    "USD/MXN": 17.400999,
    "USD/NOK": 9.66242,
    "USD/NZD": 1.7087,
    "USD/AUD": 1.4291,
    "USD/KRW": 1480.579956,
    "USD/CNY": 6.7677,
    "EUR/BRL": 5.8142
  }
}