{
  "updated_at": "2026-07-13T18:04:52.783161+00:00",
  "source": "yfinance",
  "variacoes": {},
  "precos": {
    "GOLD": 4001.600098,
    "COPPER": 6.274,
    "CL": 77.290001,
    "OSLO": 2290.949951,
    "ZS": 1198.25,
    "YMH26": 52736.0,
    "GDOW": 52503.78125,
    "VALE.K": 14.115,
    "PBR": 17.8599,
    "EWZ": 35.450001,
    "XLF": 55.955002,
    "XLP": 84.654999,
    "XLE": 56.814999,
    "XME": 101.82,
    "EEM": 64.565002,
    "SOXX.O": 553.710022,
    ".BSESN": 77616.398438,
    "CHINA": 3913.794,
    "MINERIO_SINA": 161.91,
    "DX": 101.245003,
    "VX": 16.719999,
    "USD/MXN": 17.5287,
    "USD/NOK": 9.78097,
    "USD/NZD": 1.7377,
    "USD/AUD": 1.4444,
    "USD/KRW": 1497.040039,
    "USD/CNY": 6.7677,
    "EUR/BRL": 5.8402
  }
}