{
  "updated_at": "2026-06-30T11:49:11.483910+00:00",
  "source": "yfinance",
  "variacoes": {},
  "precos": {
    "GOLD": 4045.0,
    "COPPER": 6.252,
    "CL": 70.800003,
    "OSLO": 2227.590088,
    "ZS": 1135.0,
    "YMH26": 52628.0,
    "GDOW": 52182.738281,
    "VALE.K": 15.03,
    "PBR": 16.280001,
    "EWZ": 34.549999,
    "XLF": 53.720001,
    "XLP": 84.370003,
    "XLE": 53.580002,
    "XME": 106.519997,
    "EEM": 67.43,
    "SOXX.O": 614.349976,
    ".BSESN": 76478.671875,
    "CHINA": 4094.397217,
    "MINERIO_SINA": 161.91,
    "DX": 101.419998,
    "VX": 17.49,
    "USD/MXN": 17.4596,
    "USD/NOK": 9.91695,
    "USD/NZD": 1.7664,
    "USD/AUD": 1.4513,
    "USD/KRW": 1551.0,
    "USD/CNY": 6.7738,
    "EUR/BRL": 5.8875
  }
}